QtMPLtools/__init__.py
QtMPLtools/matplotlibwidgets.py
QtMPLtools/mplpolarplugin.py
QtMPLtools/mplrectplugin.py
QtMPLtools/mplsurface2Dplugin.py
QtMPLtools/mplsurface3Dplugin.py
QtMPLtools/Test Trial/chamberLogo.jpg
QtMPLtools/Test Trial/farFieldsData.csv
QtMPLtools/Test Trial/gui.py
QtMPLtools/Test Trial/gui.ui
QtMPLtools/figures/polar.ico
QtMPLtools/figures/rect.ico
QtMPLtools/figures/surface2D.ico
QtMPLtools/figures/surface3D.ico
QtMPLtools/scripts/__init__.py
QtMPLtools/scripts/designer.py
QtMPLtools-1.0.5.dist-info/LICENSE
QtMPLtools-1.0.5.dist-info/METADATA
QtMPLtools-1.0.5.dist-info/WHEEL
QtMPLtools-1.0.5.dist-info/entry_points.txt
QtMPLtools-1.0.5.dist-info/top_level.txt
QtMPLtools-1.0.5.dist-info/RECORD
