Metadata-Version: 2.1
Name: QtMPLtools
Version: 1.0.5
Summary: Matplotlib plugins for Qt designer
Home-page: https://github.com/dresis/QtMPLtools
Author: Andy Velasco
Author-email: 
License: MIT
Keywords: python,qt,matplotlib,plugins,plots
Classifier: Development Status :: 3 - Alpha
Classifier: Intended Audience :: Developers
Classifier: Programming Language :: Python :: 3.11
Classifier: Operating System :: Microsoft :: Windows
Requires-Python: >=3.8
License-File: LICENSE
Requires-Dist: matplotlib
Requires-Dist: PyQt6
Requires-Dist: pyqt6-tools
Requires-Dist: qtpy
